setup.cfg
setup.py
test
WSGIFilter.egg-info/PKG-INFO
WSGIFilter.egg-info/SOURCES.txt
WSGIFilter.egg-info/dependency_links.txt
WSGIFilter.egg-info/entry_points.txt
WSGIFilter.egg-info/not-zip-safe
WSGIFilter.egg-info/paster_plugins.txt
WSGIFilter.egg-info/requires.txt
WSGIFilter.egg-info/top_level.txt
docs/index.txt
docs/license.txt
docs/todo.txt
tests/conftest.py
tests/test_filters.py
tests/test_relocate.txt
tests/test_wsgi.py
tests/test-data/foo.html
tests/test-data/index.html
wsgifilter/__init__.py
wsgifilter/cache_utils.py
wsgifilter/filter.py
wsgifilter/fixuplinks.py
wsgifilter/htmlserialize.py
wsgifilter/lxmldoctest.py
wsgifilter/proxyapp.py
wsgifilter/proxycommand.py
wsgifilter/relocateresponse.py
wsgifilter/resource_fetcher.py
wsgifilter/examples/__init__.py
wsgifilter/examples/testingvars.py
wsgifilter/fixtures/__init__.py
wsgifilter/fixtures/cache_fixture.py