Metadata-Version: 1.0
Name: WSGIFilter
Version: 0.2
Summary: Abstract base class / framework for building output-filtering WSGI middleware
Home-page: http://pythonpaste.org/wsgifilter/
Author: Ian Bicking
Author-email: ianb@colorstudy.com
License: MIT
Keywords: wsgi middleware webdev
Platform: UNKNOWN
Classifier: Development Status :: 3 - Alpha
Classifier: Intended Audience :: Developers
Classifier: Framework :: Paste
Classifier: License :: OSI Approved :: MIT License
Classifier: Topic :: Internet :: WWW/HTTP :: WSGI
